ccc/__init__.py
ccc/cache.py
ccc/collocates.py
ccc/concordances.py
ccc/counts.py
ccc/cqp.py
ccc/cqpy.py
ccc/cwb.py
ccc/discoursemes.py
ccc/dumps.py
ccc/frames.py
ccc/keywords.py
ccc/ufa.py
ccc/utils.py
ccc/version.py
tests/__init__.py
tests/conftest.py
tests/test_01_utils.py
tests/test_02_cqp.py
tests/test_03_cache.py
tests/test_04_cwb.py
tests/test_05_concordance.py
tests/test_06_cqpy.py
tests/test_07_counts.py
tests/test_08_collocates.py
tests/test_09_keywords.py
tests/test_10_dumps.py
tests/test_11_ufa.py
tests/test_12_discoursemes.py
cwb_ccc-0.9.15.dist-info/LICENSE
cwb_ccc-0.9.15.dist-info/METADATA
cwb_ccc-0.9.15.dist-info/WHEEL
cwb_ccc-0.9.15.dist-info/top_level.txt
cwb_ccc-0.9.15.dist-info/RECORD
