Metadata-Version: 2.1
Name: cwb-ccc
Version: 0.9.15
Summary: CWB wrapper to extract concordances and collocates
Home-page: https://github.com/ausgerechnet/cwb-ccc
Author: Philipp Heinrich
Author-email: philipp.heinrich@fau.de
License: UNKNOWN
Platform: UNKNOWN
Classifier: Development Status :: 3 - Alpha
Classifier: Programming Language :: Python :: 3
Classifier: License :: OSI Approved :: GNU General Public License v3 or later (GPLv3+)
Classifier: Operating System :: Unix
Requires-Python: >=3.7.1
Requires-Dist: association-measures (>=0.1.5)
Requires-Dist: cwb-python (>=0.2.2)
Requires-Dist: pandas (>=1.2.0)
Requires-Dist: numexpr (>=2.7.1)
Requires-Dist: Bottleneck (>=1.3.2)
Requires-Dist: unidecode (>=1.1.1)
Requires-Dist: pyyaml (>=5.4.1)
